breast_cancer_toolkit/__init__.py
breast_cancer_toolkit/cli.py
breast_cancer_toolkit/webapp.py
breast_cancer_toolkit/io/DicomImagePlugin.py
breast_cancer_toolkit/io/__init__.py
breast_cancer_toolkit/io/assets.py
breast_cancer_toolkit/rembg/__init__.py
breast_cancer_toolkit-1.1.0.dist-info/LICENSE.txt
breast_cancer_toolkit-1.1.0.dist-info/METADATA
breast_cancer_toolkit-1.1.0.dist-info/WHEEL
breast_cancer_toolkit-1.1.0.dist-info/entry_points.txt
breast_cancer_toolkit-1.1.0.dist-info/top_level.txt
breast_cancer_toolkit-1.1.0.dist-info/RECORD
