Metadata-Version: 2.1
Name: breast-cancer-toolkit
Version: 1.1.0
Summary: Machine learning toolkit designed to support data scientists in breast cancer analysis.
Home-page: https://github.com/pyscaffold/pyscaffold/
Author: sanchezcarlosjr
Author-email: 24639141+sanchezcarlosjr@users.noreply.github.com
License: MIT
Project-URL: Documentation, https://pyscaffold.org/
Platform: any
Classifier: Development Status :: 4 - Beta
Classifier: Programming Language :: Python
License-File: LICENSE.txt
Requires-Dist: typer[all]
Requires-Dist: gradio
Requires-Dist: pydantic
Requires-Dist: pandas
Requires-Dist: numpy
Requires-Dist: fastapi
Requires-Dist: keyring
Requires-Dist: python-magic
Requires-Dist: pillow-heif
Requires-Dist: pydicom
Requires-Dist: pillow
Requires-Dist: opencv-python
Requires-Dist: pylibjpeg[all]
Requires-Dist: python-gdcm
Requires-Dist: importlib-metadata ; python_version < "3.10"
Provides-Extra: yolo
Requires-Dist: ultralytics ; extra == 'yolo'
Requires-Dist: opencv-python-headless ; extra == 'yolo'
Provides-Extra: testing
Requires-Dist: setuptools ; extra == 'testing'
Requires-Dist: pytest ; extra == 'testing'
Requires-Dist: pytest-cov ; extra == 'testing'
